[
  {
    "slug": "roast-ex-savage-instagram",
    "title": "Savage Ways to Roast Your Ex on Instagram",
    "description": "Hilarious savage roasts for your ex's Instagram. Get the perfect comeback with our AI-powered roast generator.",
    "category": "roast-generator",
    "subcategory": "ex",
    "tags": [
      "ex",
      "savage",
      "roast",
      "instagram",
      "funny"
    ],
    "content": {
      "intro": "Ready to deliver the perfect savage roast to your ex? We've got you covered.",
      "disclaimer": "Remember: Good roasts are funny, not hurtful. Keep it savage but respectful!"
    },
    "relatedPages": [
      "/instagram-roast-generator",
      "/roast-ideas-ex",
      "/best-roast-2025"
    ],
    "examples": [
      "Your ex posts screams \"savage desperation\"",
      "That savage filter can't hide your ex energy",
      "Classic ex move - thinking this is savage"
    ]
  },
  {
    "slug": "roast-ex-funny-instagram",
    "title": "Funny Ways to Roast Your Ex on Instagram",
    "description": "Hilarious funny roasts for your ex's Instagram. Get the perfect comeback with our AI-powered roast generator.",
    "category": "roast-generator",
    "subcategory": "ex",
    "tags": [
      "ex",
      "funny",
      "roast",
      "instagram",
      "funny"
    ],
    "content": {
      "intro": "Ready to deliver the perfect funny roast to your ex? We've got you covered.",
      "disclaimer": "Remember: Good roasts are funny, not hurtful. Keep it funny but respectful!"
    },
    "relatedPages": [
      "/instagram-roast-generator",
      "/roast-ideas-ex",
      "/best-roast-2025"
    ],
    "examples": [
      "Your ex posts screams \"funny desperation\"",
      "That funny filter can't hide your ex energy",
      "Classic ex move - thinking this is funny"
    ]
  },
  {
    "slug": "roast-ex-clever-instagram",
    "title": "Clever Ways to Roast Your Ex on Instagram",
    "description": "Hilarious clever roasts for your ex's Instagram. Get the perfect comeback with our AI-powered roast generator.",
    "category": "roast-generator",
    "subcategory": "ex",
    "tags": [
      "ex",
      "clever",
      "roast",
      "instagram",
      "funny"
    ],
    "content": {
      "intro": "Ready to deliver the perfect clever roast to your ex? We've got you covered.",
      "disclaimer": "Remember: Good roasts are funny, not hurtful. Keep it clever but respectful!"
    },
    "relatedPages": [
      "/instagram-roast-generator",
      "/roast-ideas-ex",
      "/best-roast-2025"
    ],
    "examples": [
      "Your ex posts screams \"clever desperation\"",
      "That clever filter can't hide your ex energy",
      "Classic ex move - thinking this is clever"
    ]
  },
  {
    "slug": "roast-ex-witty-instagram",
    "title": "Witty Ways to Roast Your Ex on Instagram",
    "description": "Hilarious witty roasts for your ex's Instagram. Get the perfect comeback with our AI-powered roast generator.",
    "category": "roast-generator",
    "subcategory": "ex",
    "tags": [
      "ex",
      "witty",
      "roast",
      "instagram",
      "funny"
    ],
    "content": {
      "intro": "Ready to deliver the perfect witty roast to your ex? We've got you covered.",
      "disclaimer": "Remember: Good roasts are funny, not hurtful. Keep it witty but respectful!"
    },
    "relatedPages": [
      "/instagram-roast-generator",
      "/roast-ideas-ex",
      "/best-roast-2025"
    ],
    "examples": [
      "Your ex posts screams \"witty desperation\"",
      "That witty filter can't hide your ex energy",
      "Classic ex move - thinking this is witty"
    ]
  },
  {
    "slug": "roast-friend-savage-instagram",
    "title": "Savage Ways to Roast Your Friend on Instagram",
    "description": "Hilarious savage roasts for your friend's Instagram. Get the perfect comeback with our AI-powered roast generator.",
    "category": "roast-generator",
    "subcategory": "friend",
    "tags": [
      "friend",
      "savage",
      "roast",
      "instagram",
      "funny"
    ],
    "content": {
      "intro": "Ready to deliver the perfect savage roast to your friend? We've got you covered.",
      "disclaimer": "Remember: Good roasts are funny, not hurtful. Keep it savage but respectful!"
    },
    "relatedPages": [
      "/instagram-roast-generator",
      "/roast-ideas-friend",
      "/best-roast-2025"
    ],
    "examples": [
      "Your friend posts screams \"savage desperation\"",
      "That savage filter can't hide your friend energy",
      "Classic friend move - thinking this is savage"
    ]
  },
  {
    "slug": "roast-friend-funny-instagram",
    "title": "Funny Ways to Roast Your Friend on Instagram",
    "description": "Hilarious funny roasts for your friend's Instagram. Get the perfect comeback with our AI-powered roast generator.",
    "category": "roast-generator",
    "subcategory": "friend",
    "tags": [
      "friend",
      "funny",
      "roast",
      "instagram",
      "funny"
    ],
    "content": {
      "intro": "Ready to deliver the perfect funny roast to your friend? We've got you covered.",
      "disclaimer": "Remember: Good roasts are funny, not hurtful. Keep it funny but respectful!"
    },
    "relatedPages": [
      "/instagram-roast-generator",
      "/roast-ideas-friend",
      "/best-roast-2025"
    ],
    "examples": [
      "Your friend posts screams \"funny desperation\"",
      "That funny filter can't hide your friend energy",
      "Classic friend move - thinking this is funny"
    ]
  },
  {
    "slug": "roast-friend-clever-instagram",
    "title": "Clever Ways to Roast Your Friend on Instagram",
    "description": "Hilarious clever roasts for your friend's Instagram. Get the perfect comeback with our AI-powered roast generator.",
    "category": "roast-generator",
    "subcategory": "friend",
    "tags": [
      "friend",
      "clever",
      "roast",
      "instagram",
      "funny"
    ],
    "content": {
      "intro": "Ready to deliver the perfect clever roast to your friend? We've got you covered.",
      "disclaimer": "Remember: Good roasts are funny, not hurtful. Keep it clever but respectful!"
    },
    "relatedPages": [
      "/instagram-roast-generator",
      "/roast-ideas-friend",
      "/best-roast-2025"
    ],
    "examples": [
      "Your friend posts screams \"clever desperation\"",
      "That clever filter can't hide your friend energy",
      "Classic friend move - thinking this is clever"
    ]
  },
  {
    "slug": "roast-friend-witty-instagram",
    "title": "Witty Ways to Roast Your Friend on Instagram",
    "description": "Hilarious witty roasts for your friend's Instagram. Get the perfect comeback with our AI-powered roast generator.",
    "category": "roast-generator",
    "subcategory": "friend",
    "tags": [
      "friend",
      "witty",
      "roast",
      "instagram",
      "funny"
    ],
    "content": {
      "intro": "Ready to deliver the perfect witty roast to your friend? We've got you covered.",
      "disclaimer": "Remember: Good roasts are funny, not hurtful. Keep it witty but respectful!"
    },
    "relatedPages": [
      "/instagram-roast-generator",
      "/roast-ideas-friend",
      "/best-roast-2025"
    ],
    "examples": [
      "Your friend posts screams \"witty desperation\"",
      "That witty filter can't hide your friend energy",
      "Classic friend move - thinking this is witty"
    ]
  },
  {
    "slug": "roast-sibling-savage-instagram",
    "title": "Savage Ways to Roast Your Sibling on Instagram",
    "description": "Hilarious savage roasts for your sibling's Instagram. Get the perfect comeback with our AI-powered roast generator.",
    "category": "roast-generator",
    "subcategory": "sibling",
    "tags": [
      "sibling",
      "savage",
      "roast",
      "instagram",
      "funny"
    ],
    "content": {
      "intro": "Ready to deliver the perfect savage roast to your sibling? We've got you covered.",
      "disclaimer": "Remember: Good roasts are funny, not hurtful. Keep it savage but respectful!"
    },
    "relatedPages": [
      "/instagram-roast-generator",
      "/roast-ideas-sibling",
      "/best-roast-2025"
    ],
    "examples": [
      "Your sibling posts screams \"savage desperation\"",
      "That savage filter can't hide your sibling energy",
      "Classic sibling move - thinking this is savage"
    ]
  },
  {
    "slug": "roast-sibling-funny-instagram",
    "title": "Funny Ways to Roast Your Sibling on Instagram",
    "description": "Hilarious funny roasts for your sibling's Instagram. Get the perfect comeback with our AI-powered roast generator.",
    "category": "roast-generator",
    "subcategory": "sibling",
    "tags": [
      "sibling",
      "funny",
      "roast",
      "instagram",
      "funny"
    ],
    "content": {
      "intro": "Ready to deliver the perfect funny roast to your sibling? We've got you covered.",
      "disclaimer": "Remember: Good roasts are funny, not hurtful. Keep it funny but respectful!"
    },
    "relatedPages": [
      "/instagram-roast-generator",
      "/roast-ideas-sibling",
      "/best-roast-2025"
    ],
    "examples": [
      "Your sibling posts screams \"funny desperation\"",
      "That funny filter can't hide your sibling energy",
      "Classic sibling move - thinking this is funny"
    ]
  },
  {
    "slug": "roast-sibling-clever-instagram",
    "title": "Clever Ways to Roast Your Sibling on Instagram",
    "description": "Hilarious clever roasts for your sibling's Instagram. Get the perfect comeback with our AI-powered roast generator.",
    "category": "roast-generator",
    "subcategory": "sibling",
    "tags": [
      "sibling",
      "clever",
      "roast",
      "instagram",
      "funny"
    ],
    "content": {
      "intro": "Ready to deliver the perfect clever roast to your sibling? We've got you covered.",
      "disclaimer": "Remember: Good roasts are funny, not hurtful. Keep it clever but respectful!"
    },
    "relatedPages": [
      "/instagram-roast-generator",
      "/roast-ideas-sibling",
      "/best-roast-2025"
    ],
    "examples": [
      "Your sibling posts screams \"clever desperation\"",
      "That clever filter can't hide your sibling energy",
      "Classic sibling move - thinking this is clever"
    ]
  },
  {
    "slug": "roast-sibling-witty-instagram",
    "title": "Witty Ways to Roast Your Sibling on Instagram",
    "description": "Hilarious witty roasts for your sibling's Instagram. Get the perfect comeback with our AI-powered roast generator.",
    "category": "roast-generator",
    "subcategory": "sibling",
    "tags": [
      "sibling",
      "witty",
      "roast",
      "instagram",
      "funny"
    ],
    "content": {
      "intro": "Ready to deliver the perfect witty roast to your sibling? We've got you covered.",
      "disclaimer": "Remember: Good roasts are funny, not hurtful. Keep it witty but respectful!"
    },
    "relatedPages": [
      "/instagram-roast-generator",
      "/roast-ideas-sibling",
      "/best-roast-2025"
    ],
    "examples": [
      "Your sibling posts screams \"witty desperation\"",
      "That witty filter can't hide your sibling energy",
      "Classic sibling move - thinking this is witty"
    ]
  },
  {
    "slug": "roast-coworker-savage-instagram",
    "title": "Savage Ways to Roast Your Coworker on Instagram",
    "description": "Hilarious savage roasts for your coworker's Instagram. Get the perfect comeback with our AI-powered roast generator.",
    "category": "roast-generator",
    "subcategory": "coworker",
    "tags": [
      "coworker",
      "savage",
      "roast",
      "instagram",
      "funny"
    ],
    "content": {
      "intro": "Ready to deliver the perfect savage roast to your coworker? We've got you covered.",
      "disclaimer": "Remember: Good roasts are funny, not hurtful. Keep it savage but respectful!"
    },
    "relatedPages": [
      "/instagram-roast-generator",
      "/roast-ideas-coworker",
      "/best-roast-2025"
    ],
    "examples": [
      "Your coworker posts screams \"savage desperation\"",
      "That savage filter can't hide your coworker energy",
      "Classic coworker move - thinking this is savage"
    ]
  },
  {
    "slug": "roast-coworker-funny-instagram",
    "title": "Funny Ways to Roast Your Coworker on Instagram",
    "description": "Hilarious funny roasts for your coworker's Instagram. Get the perfect comeback with our AI-powered roast generator.",
    "category": "roast-generator",
    "subcategory": "coworker",
    "tags": [
      "coworker",
      "funny",
      "roast",
      "instagram",
      "funny"
    ],
    "content": {
      "intro": "Ready to deliver the perfect funny roast to your coworker? We've got you covered.",
      "disclaimer": "Remember: Good roasts are funny, not hurtful. Keep it funny but respectful!"
    },
    "relatedPages": [
      "/instagram-roast-generator",
      "/roast-ideas-coworker",
      "/best-roast-2025"
    ],
    "examples": [
      "Your coworker posts screams \"funny desperation\"",
      "That funny filter can't hide your coworker energy",
      "Classic coworker move - thinking this is funny"
    ]
  },
  {
    "slug": "roast-coworker-clever-instagram",
    "title": "Clever Ways to Roast Your Coworker on Instagram",
    "description": "Hilarious clever roasts for your coworker's Instagram. Get the perfect comeback with our AI-powered roast generator.",
    "category": "roast-generator",
    "subcategory": "coworker",
    "tags": [
      "coworker",
      "clever",
      "roast",
      "instagram",
      "funny"
    ],
    "content": {
      "intro": "Ready to deliver the perfect clever roast to your coworker? We've got you covered.",
      "disclaimer": "Remember: Good roasts are funny, not hurtful. Keep it clever but respectful!"
    },
    "relatedPages": [
      "/instagram-roast-generator",
      "/roast-ideas-coworker",
      "/best-roast-2025"
    ],
    "examples": [
      "Your coworker posts screams \"clever desperation\"",
      "That clever filter can't hide your coworker energy",
      "Classic coworker move - thinking this is clever"
    ]
  },
  {
    "slug": "roast-coworker-witty-instagram",
    "title": "Witty Ways to Roast Your Coworker on Instagram",
    "description": "Hilarious witty roasts for your coworker's Instagram. Get the perfect comeback with our AI-powered roast generator.",
    "category": "roast-generator",
    "subcategory": "coworker",
    "tags": [
      "coworker",
      "witty",
      "roast",
      "instagram",
      "funny"
    ],
    "content": {
      "intro": "Ready to deliver the perfect witty roast to your coworker? We've got you covered.",
      "disclaimer": "Remember: Good roasts are funny, not hurtful. Keep it witty but respectful!"
    },
    "relatedPages": [
      "/instagram-roast-generator",
      "/roast-ideas-coworker",
      "/best-roast-2025"
    ],
    "examples": [
      "Your coworker posts screams \"witty desperation\"",
      "That witty filter can't hide your coworker energy",
      "Classic coworker move - thinking this is witty"
    ]
  },
  {
    "slug": "roast-celebrity-savage-instagram",
    "title": "Savage Ways to Roast Your Celebrity on Instagram",
    "description": "Hilarious savage roasts for your celebrity's Instagram. Get the perfect comeback with our AI-powered roast generator.",
    "category": "roast-generator",
    "subcategory": "celebrity",
    "tags": [
      "celebrity",
      "savage",
      "roast",
      "instagram",
      "funny"
    ],
    "content": {
      "intro": "Ready to deliver the perfect savage roast to your celebrity? We've got you covered.",
      "disclaimer": "Remember: Good roasts are funny, not hurtful. Keep it savage but respectful!"
    },
    "relatedPages": [
      "/instagram-roast-generator",
      "/roast-ideas-celebrity",
      "/best-roast-2025"
    ],
    "examples": [
      "Your celebrity posts screams \"savage desperation\"",
      "That savage filter can't hide your celebrity energy",
      "Classic celebrity move - thinking this is savage"
    ]
  },
  {
    "slug": "roast-celebrity-funny-instagram",
    "title": "Funny Ways to Roast Your Celebrity on Instagram",
    "description": "Hilarious funny roasts for your celebrity's Instagram. Get the perfect comeback with our AI-powered roast generator.",
    "category": "roast-generator",
    "subcategory": "celebrity",
    "tags": [
      "celebrity",
      "funny",
      "roast",
      "instagram",
      "funny"
    ],
    "content": {
      "intro": "Ready to deliver the perfect funny roast to your celebrity? We've got you covered.",
      "disclaimer": "Remember: Good roasts are funny, not hurtful. Keep it funny but respectful!"
    },
    "relatedPages": [
      "/instagram-roast-generator",
      "/roast-ideas-celebrity",
      "/best-roast-2025"
    ],
    "examples": [
      "Your celebrity posts screams \"funny desperation\"",
      "That funny filter can't hide your celebrity energy",
      "Classic celebrity move - thinking this is funny"
    ]
  },
  {
    "slug": "roast-celebrity-clever-instagram",
    "title": "Clever Ways to Roast Your Celebrity on Instagram",
    "description": "Hilarious clever roasts for your celebrity's Instagram. Get the perfect comeback with our AI-powered roast generator.",
    "category": "roast-generator",
    "subcategory": "celebrity",
    "tags": [
      "celebrity",
      "clever",
      "roast",
      "instagram",
      "funny"
    ],
    "content": {
      "intro": "Ready to deliver the perfect clever roast to your celebrity? We've got you covered.",
      "disclaimer": "Remember: Good roasts are funny, not hurtful. Keep it clever but respectful!"
    },
    "relatedPages": [
      "/instagram-roast-generator",
      "/roast-ideas-celebrity",
      "/best-roast-2025"
    ],
    "examples": [
      "Your celebrity posts screams \"clever desperation\"",
      "That clever filter can't hide your celebrity energy",
      "Classic celebrity move - thinking this is clever"
    ]
  },
  {
    "slug": "roast-celebrity-witty-instagram",
    "title": "Witty Ways to Roast Your Celebrity on Instagram",
    "description": "Hilarious witty roasts for your celebrity's Instagram. Get the perfect comeback with our AI-powered roast generator.",
    "category": "roast-generator",
    "subcategory": "celebrity",
    "tags": [
      "celebrity",
      "witty",
      "roast",
      "instagram",
      "funny"
    ],
    "content": {
      "intro": "Ready to deliver the perfect witty roast to your celebrity? We've got you covered.",
      "disclaimer": "Remember: Good roasts are funny, not hurtful. Keep it witty but respectful!"
    },
    "relatedPages": [
      "/instagram-roast-generator",
      "/roast-ideas-celebrity",
      "/best-roast-2025"
    ],
    "examples": [
      "Your celebrity posts screams \"witty desperation\"",
      "That witty filter can't hide your celebrity energy",
      "Classic celebrity move - thinking this is witty"
    ]
  },
  {
    "slug": "roast-influencer-savage-instagram",
    "title": "Savage Ways to Roast Your Influencer on Instagram",
    "description": "Hilarious savage roasts for your influencer's Instagram. Get the perfect comeback with our AI-powered roast generator.",
    "category": "roast-generator",
    "subcategory": "influencer",
    "tags": [
      "influencer",
      "savage",
      "roast",
      "instagram",
      "funny"
    ],
    "content": {
      "intro": "Ready to deliver the perfect savage roast to your influencer? We've got you covered.",
      "disclaimer": "Remember: Good roasts are funny, not hurtful. Keep it savage but respectful!"
    },
    "relatedPages": [
      "/instagram-roast-generator",
      "/roast-ideas-influencer",
      "/best-roast-2025"
    ],
    "examples": [
      "Your influencer posts screams \"savage desperation\"",
      "That savage filter can't hide your influencer energy",
      "Classic influencer move - thinking this is savage"
    ]
  },
  {
    "slug": "roast-influencer-funny-instagram",
    "title": "Funny Ways to Roast Your Influencer on Instagram",
    "description": "Hilarious funny roasts for your influencer's Instagram. Get the perfect comeback with our AI-powered roast generator.",
    "category": "roast-generator",
    "subcategory": "influencer",
    "tags": [
      "influencer",
      "funny",
      "roast",
      "instagram",
      "funny"
    ],
    "content": {
      "intro": "Ready to deliver the perfect funny roast to your influencer? We've got you covered.",
      "disclaimer": "Remember: Good roasts are funny, not hurtful. Keep it funny but respectful!"
    },
    "relatedPages": [
      "/instagram-roast-generator",
      "/roast-ideas-influencer",
      "/best-roast-2025"
    ],
    "examples": [
      "Your influencer posts screams \"funny desperation\"",
      "That funny filter can't hide your influencer energy",
      "Classic influencer move - thinking this is funny"
    ]
  },
  {
    "slug": "roast-influencer-clever-instagram",
    "title": "Clever Ways to Roast Your Influencer on Instagram",
    "description": "Hilarious clever roasts for your influencer's Instagram. Get the perfect comeback with our AI-powered roast generator.",
    "category": "roast-generator",
    "subcategory": "influencer",
    "tags": [
      "influencer",
      "clever",
      "roast",
      "instagram",
      "funny"
    ],
    "content": {
      "intro": "Ready to deliver the perfect clever roast to your influencer? We've got you covered.",
      "disclaimer": "Remember: Good roasts are funny, not hurtful. Keep it clever but respectful!"
    },
    "relatedPages": [
      "/instagram-roast-generator",
      "/roast-ideas-influencer",
      "/best-roast-2025"
    ],
    "examples": [
      "Your influencer posts screams \"clever desperation\"",
      "That clever filter can't hide your influencer energy",
      "Classic influencer move - thinking this is clever"
    ]
  },
  {
    "slug": "roast-influencer-witty-instagram",
    "title": "Witty Ways to Roast Your Influencer on Instagram",
    "description": "Hilarious witty roasts for your influencer's Instagram. Get the perfect comeback with our AI-powered roast generator.",
    "category": "roast-generator",
    "subcategory": "influencer",
    "tags": [
      "influencer",
      "witty",
      "roast",
      "instagram",
      "funny"
    ],
    "content": {
      "intro": "Ready to deliver the perfect witty roast to your influencer? We've got you covered.",
      "disclaimer": "Remember: Good roasts are funny, not hurtful. Keep it witty but respectful!"
    },
    "relatedPages": [
      "/instagram-roast-generator",
      "/roast-ideas-influencer",
      "/best-roast-2025"
    ],
    "examples": [
      "Your influencer posts screams \"witty desperation\"",
      "That witty filter can't hide your influencer energy",
      "Classic influencer move - thinking this is witty"
    ]
  },
  {
    "slug": "roast-gym-bro-savage-instagram",
    "title": "Savage Ways to Roast Your Gym-bro on Instagram",
    "description": "Hilarious savage roasts for your gym-bro's Instagram. Get the perfect comeback with our AI-powered roast generator.",
    "category": "roast-generator",
    "subcategory": "gym-bro",
    "tags": [
      "gym-bro",
      "savage",
      "roast",
      "instagram",
      "funny"
    ],
    "content": {
      "intro": "Ready to deliver the perfect savage roast to your gym-bro? We've got you covered.",
      "disclaimer": "Remember: Good roasts are funny, not hurtful. Keep it savage but respectful!"
    },
    "relatedPages": [
      "/instagram-roast-generator",
      "/roast-ideas-gym-bro",
      "/best-roast-2025"
    ],
    "examples": [
      "Your gym-bro posts screams \"savage desperation\"",
      "That savage filter can't hide your gym-bro energy",
      "Classic gym-bro move - thinking this is savage"
    ]
  },
  {
    "slug": "roast-gym-bro-funny-instagram",
    "title": "Funny Ways to Roast Your Gym-bro on Instagram",
    "description": "Hilarious funny roasts for your gym-bro's Instagram. Get the perfect comeback with our AI-powered roast generator.",
    "category": "roast-generator",
    "subcategory": "gym-bro",
    "tags": [
      "gym-bro",
      "funny",
      "roast",
      "instagram",
      "funny"
    ],
    "content": {
      "intro": "Ready to deliver the perfect funny roast to your gym-bro? We've got you covered.",
      "disclaimer": "Remember: Good roasts are funny, not hurtful. Keep it funny but respectful!"
    },
    "relatedPages": [
      "/instagram-roast-generator",
      "/roast-ideas-gym-bro",
      "/best-roast-2025"
    ],
    "examples": [
      "Your gym-bro posts screams \"funny desperation\"",
      "That funny filter can't hide your gym-bro energy",
      "Classic gym-bro move - thinking this is funny"
    ]
  },
  {
    "slug": "roast-gym-bro-clever-instagram",
    "title": "Clever Ways to Roast Your Gym-bro on Instagram",
    "description": "Hilarious clever roasts for your gym-bro's Instagram. Get the perfect comeback with our AI-powered roast generator.",
    "category": "roast-generator",
    "subcategory": "gym-bro",
    "tags": [
      "gym-bro",
      "clever",
      "roast",
      "instagram",
      "funny"
    ],
    "content": {
      "intro": "Ready to deliver the perfect clever roast to your gym-bro? We've got you covered.",
      "disclaimer": "Remember: Good roasts are funny, not hurtful. Keep it clever but respectful!"
    },
    "relatedPages": [
      "/instagram-roast-generator",
      "/roast-ideas-gym-bro",
      "/best-roast-2025"
    ],
    "examples": [
      "Your gym-bro posts screams \"clever desperation\"",
      "That clever filter can't hide your gym-bro energy",
      "Classic gym-bro move - thinking this is clever"
    ]
  },
  {
    "slug": "roast-gym-bro-witty-instagram",
    "title": "Witty Ways to Roast Your Gym-bro on Instagram",
    "description": "Hilarious witty roasts for your gym-bro's Instagram. Get the perfect comeback with our AI-powered roast generator.",
    "category": "roast-generator",
    "subcategory": "gym-bro",
    "tags": [
      "gym-bro",
      "witty",
      "roast",
      "instagram",
      "funny"
    ],
    "content": {
      "intro": "Ready to deliver the perfect witty roast to your gym-bro? We've got you covered.",
      "disclaimer": "Remember: Good roasts are funny, not hurtful. Keep it witty but respectful!"
    },
    "relatedPages": [
      "/instagram-roast-generator",
      "/roast-ideas-gym-bro",
      "/best-roast-2025"
    ],
    "examples": [
      "Your gym-bro posts screams \"witty desperation\"",
      "That witty filter can't hide your gym-bro energy",
      "Classic gym-bro move - thinking this is witty"
    ]
  },
  {
    "slug": "roast-foodie-savage-instagram",
    "title": "Savage Ways to Roast Your Foodie on Instagram",
    "description": "Hilarious savage roasts for your foodie's Instagram. Get the perfect comeback with our AI-powered roast generator.",
    "category": "roast-generator",
    "subcategory": "foodie",
    "tags": [
      "foodie",
      "savage",
      "roast",
      "instagram",
      "funny"
    ],
    "content": {
      "intro": "Ready to deliver the perfect savage roast to your foodie? We've got you covered.",
      "disclaimer": "Remember: Good roasts are funny, not hurtful. Keep it savage but respectful!"
    },
    "relatedPages": [
      "/instagram-roast-generator",
      "/roast-ideas-foodie",
      "/best-roast-2025"
    ],
    "examples": [
      "Your foodie posts screams \"savage desperation\"",
      "That savage filter can't hide your foodie energy",
      "Classic foodie move - thinking this is savage"
    ]
  },
  {
    "slug": "roast-foodie-funny-instagram",
    "title": "Funny Ways to Roast Your Foodie on Instagram",
    "description": "Hilarious funny roasts for your foodie's Instagram. Get the perfect comeback with our AI-powered roast generator.",
    "category": "roast-generator",
    "subcategory": "foodie",
    "tags": [
      "foodie",
      "funny",
      "roast",
      "instagram",
      "funny"
    ],
    "content": {
      "intro": "Ready to deliver the perfect funny roast to your foodie? We've got you covered.",
      "disclaimer": "Remember: Good roasts are funny, not hurtful. Keep it funny but respectful!"
    },
    "relatedPages": [
      "/instagram-roast-generator",
      "/roast-ideas-foodie",
      "/best-roast-2025"
    ],
    "examples": [
      "Your foodie posts screams \"funny desperation\"",
      "That funny filter can't hide your foodie energy",
      "Classic foodie move - thinking this is funny"
    ]
  },
  {
    "slug": "roast-foodie-clever-instagram",
    "title": "Clever Ways to Roast Your Foodie on Instagram",
    "description": "Hilarious clever roasts for your foodie's Instagram. Get the perfect comeback with our AI-powered roast generator.",
    "category": "roast-generator",
    "subcategory": "foodie",
    "tags": [
      "foodie",
      "clever",
      "roast",
      "instagram",
      "funny"
    ],
    "content": {
      "intro": "Ready to deliver the perfect clever roast to your foodie? We've got you covered.",
      "disclaimer": "Remember: Good roasts are funny, not hurtful. Keep it clever but respectful!"
    },
    "relatedPages": [
      "/instagram-roast-generator",
      "/roast-ideas-foodie",
      "/best-roast-2025"
    ],
    "examples": [
      "Your foodie posts screams \"clever desperation\"",
      "That clever filter can't hide your foodie energy",
      "Classic foodie move - thinking this is clever"
    ]
  },
  {
    "slug": "roast-foodie-witty-instagram",
    "title": "Witty Ways to Roast Your Foodie on Instagram",
    "description": "Hilarious witty roasts for your foodie's Instagram. Get the perfect comeback with our AI-powered roast generator.",
    "category": "roast-generator",
    "subcategory": "foodie",
    "tags": [
      "foodie",
      "witty",
      "roast",
      "instagram",
      "funny"
    ],
    "content": {
      "intro": "Ready to deliver the perfect witty roast to your foodie? We've got you covered.",
      "disclaimer": "Remember: Good roasts are funny, not hurtful. Keep it witty but respectful!"
    },
    "relatedPages": [
      "/instagram-roast-generator",
      "/roast-ideas-foodie",
      "/best-roast-2025"
    ],
    "examples": [
      "Your foodie posts screams \"witty desperation\"",
      "That witty filter can't hide your foodie energy",
      "Classic foodie move - thinking this is witty"
    ]
  },
  {
    "slug": "roast-gamer-savage-instagram",
    "title": "Savage Ways to Roast Your Gamer on Instagram",
    "description": "Hilarious savage roasts for your gamer's Instagram. Get the perfect comeback with our AI-powered roast generator.",
    "category": "roast-generator",
    "subcategory": "gamer",
    "tags": [
      "gamer",
      "savage",
      "roast",
      "instagram",
      "funny"
    ],
    "content": {
      "intro": "Ready to deliver the perfect savage roast to your gamer? We've got you covered.",
      "disclaimer": "Remember: Good roasts are funny, not hurtful. Keep it savage but respectful!"
    },
    "relatedPages": [
      "/instagram-roast-generator",
      "/roast-ideas-gamer",
      "/best-roast-2025"
    ],
    "examples": [
      "Your gamer posts screams \"savage desperation\"",
      "That savage filter can't hide your gamer energy",
      "Classic gamer move - thinking this is savage"
    ]
  },
  {
    "slug": "roast-gamer-funny-instagram",
    "title": "Funny Ways to Roast Your Gamer on Instagram",
    "description": "Hilarious funny roasts for your gamer's Instagram. Get the perfect comeback with our AI-powered roast generator.",
    "category": "roast-generator",
    "subcategory": "gamer",
    "tags": [
      "gamer",
      "funny",
      "roast",
      "instagram",
      "funny"
    ],
    "content": {
      "intro": "Ready to deliver the perfect funny roast to your gamer? We've got you covered.",
      "disclaimer": "Remember: Good roasts are funny, not hurtful. Keep it funny but respectful!"
    },
    "relatedPages": [
      "/instagram-roast-generator",
      "/roast-ideas-gamer",
      "/best-roast-2025"
    ],
    "examples": [
      "Your gamer posts screams \"funny desperation\"",
      "That funny filter can't hide your gamer energy",
      "Classic gamer move - thinking this is funny"
    ]
  },
  {
    "slug": "roast-gamer-clever-instagram",
    "title": "Clever Ways to Roast Your Gamer on Instagram",
    "description": "Hilarious clever roasts for your gamer's Instagram. Get the perfect comeback with our AI-powered roast generator.",
    "category": "roast-generator",
    "subcategory": "gamer",
    "tags": [
      "gamer",
      "clever",
      "roast",
      "instagram",
      "funny"
    ],
    "content": {
      "intro": "Ready to deliver the perfect clever roast to your gamer? We've got you covered.",
      "disclaimer": "Remember: Good roasts are funny, not hurtful. Keep it clever but respectful!"
    },
    "relatedPages": [
      "/instagram-roast-generator",
      "/roast-ideas-gamer",
      "/best-roast-2025"
    ],
    "examples": [
      "Your gamer posts screams \"clever desperation\"",
      "That clever filter can't hide your gamer energy",
      "Classic gamer move - thinking this is clever"
    ]
  },
  {
    "slug": "roast-gamer-witty-instagram",
    "title": "Witty Ways to Roast Your Gamer on Instagram",
    "description": "Hilarious witty roasts for your gamer's Instagram. Get the perfect comeback with our AI-powered roast generator.",
    "category": "roast-generator",
    "subcategory": "gamer",
    "tags": [
      "gamer",
      "witty",
      "roast",
      "instagram",
      "funny"
    ],
    "content": {
      "intro": "Ready to deliver the perfect witty roast to your gamer? We've got you covered.",
      "disclaimer": "Remember: Good roasts are funny, not hurtful. Keep it witty but respectful!"
    },
    "relatedPages": [
      "/instagram-roast-generator",
      "/roast-ideas-gamer",
      "/best-roast-2025"
    ],
    "examples": [
      "Your gamer posts screams \"witty desperation\"",
      "That witty filter can't hide your gamer energy",
      "Classic gamer move - thinking this is witty"
    ]
  },
  {
    "slug": "roast-basic-savage-instagram",
    "title": "Savage Ways to Roast Your Basic on Instagram",
    "description": "Hilarious savage roasts for your basic's Instagram. Get the perfect comeback with our AI-powered roast generator.",
    "category": "roast-generator",
    "subcategory": "basic",
    "tags": [
      "basic",
      "savage",
      "roast",
      "instagram",
      "funny"
    ],
    "content": {
      "intro": "Ready to deliver the perfect savage roast to your basic? We've got you covered.",
      "disclaimer": "Remember: Good roasts are funny, not hurtful. Keep it savage but respectful!"
    },
    "relatedPages": [
      "/instagram-roast-generator",
      "/roast-ideas-basic",
      "/best-roast-2025"
    ],
    "examples": [
      "Your basic posts screams \"savage desperation\"",
      "That savage filter can't hide your basic energy",
      "Classic basic move - thinking this is savage"
    ]
  },
  {
    "slug": "roast-basic-funny-instagram",
    "title": "Funny Ways to Roast Your Basic on Instagram",
    "description": "Hilarious funny roasts for your basic's Instagram. Get the perfect comeback with our AI-powered roast generator.",
    "category": "roast-generator",
    "subcategory": "basic",
    "tags": [
      "basic",
      "funny",
      "roast",
      "instagram",
      "funny"
    ],
    "content": {
      "intro": "Ready to deliver the perfect funny roast to your basic? We've got you covered.",
      "disclaimer": "Remember: Good roasts are funny, not hurtful. Keep it funny but respectful!"
    },
    "relatedPages": [
      "/instagram-roast-generator",
      "/roast-ideas-basic",
      "/best-roast-2025"
    ],
    "examples": [
      "Your basic posts screams \"funny desperation\"",
      "That funny filter can't hide your basic energy",
      "Classic basic move - thinking this is funny"
    ]
  },
  {
    "slug": "roast-basic-clever-instagram",
    "title": "Clever Ways to Roast Your Basic on Instagram",
    "description": "Hilarious clever roasts for your basic's Instagram. Get the perfect comeback with our AI-powered roast generator.",
    "category": "roast-generator",
    "subcategory": "basic",
    "tags": [
      "basic",
      "clever",
      "roast",
      "instagram",
      "funny"
    ],
    "content": {
      "intro": "Ready to deliver the perfect clever roast to your basic? We've got you covered.",
      "disclaimer": "Remember: Good roasts are funny, not hurtful. Keep it clever but respectful!"
    },
    "relatedPages": [
      "/instagram-roast-generator",
      "/roast-ideas-basic",
      "/best-roast-2025"
    ],
    "examples": [
      "Your basic posts screams \"clever desperation\"",
      "That clever filter can't hide your basic energy",
      "Classic basic move - thinking this is clever"
    ]
  },
  {
    "slug": "roast-basic-witty-instagram",
    "title": "Witty Ways to Roast Your Basic on Instagram",
    "description": "Hilarious witty roasts for your basic's Instagram. Get the perfect comeback with our AI-powered roast generator.",
    "category": "roast-generator",
    "subcategory": "basic",
    "tags": [
      "basic",
      "witty",
      "roast",
      "instagram",
      "funny"
    ],
    "content": {
      "intro": "Ready to deliver the perfect witty roast to your basic? We've got you covered.",
      "disclaimer": "Remember: Good roasts are funny, not hurtful. Keep it witty but respectful!"
    },
    "relatedPages": [
      "/instagram-roast-generator",
      "/roast-ideas-basic",
      "/best-roast-2025"
    ],
    "examples": [
      "Your basic posts screams \"witty desperation\"",
      "That witty filter can't hide your basic energy",
      "Classic basic move - thinking this is witty"
    ]
  }
]